madas/__init__.py
madas/analysis.py
madas/clustering.py
madas/data_framework.py
madas/fingerprint.py
madas/material.py
madas/plotting.py
madas/similarity.py
madas/utils.py
madas/apis/NOMAD_web_API.py
madas/apis/__init__.py
madas/apis/api_core.py
madas/apis/local_data_API.py
madas/backend/ASE_backend.py
madas/backend/__init__.py
madas/backend/backend_core.py
madas/backend/dictionary_backend.py
madas/fingerprints/DOS_fingerprint.py
madas/fingerprints/DUMMY_fingerprint.py
madas/fingerprints/PROP_fingerprint.py
madas/fingerprints/PTE_fingerprint.py
madas/fingerprints/SYM_fingerprint.py
madas/fingerprints/__init__.py
nomad_dos_fingerprints/DOSfingerprint.py
nomad_dos_fingerprints/__init__.py
nomad_dos_fingerprints/grid.py
nomad_dos_fingerprints/plotting.py
nomad_dos_fingerprints/similarity.py
madas-1.0.5.dist-info/LICENSE
madas-1.0.5.dist-info/METADATA
madas-1.0.5.dist-info/WHEEL
madas-1.0.5.dist-info/top_level.txt
madas-1.0.5.dist-info/RECORD
