Metadata-Version: 2.1
Name: madas
Version: 1.0.5
Summary: The MAterials DAta Similarity framework.
Author: Martin Kuban et al.
Maintainer-email: Martin Kuban <kuban@physik.hu-berlin.de>
License: Copyright 2024 The MADAS developers
Project-URL: Documentation, https://madas.readthedocs.io
Project-URL: Source, https://github.com/kubanmar/madas
Project-URL: Issues, https://github.com/kubanmar/madas/issues
Classifier: Programming Language :: Python :: 3.10
Classifier: License :: OSI Approved :: Apache Software License
Classifier: Operating System :: POSIX :: Linux
Requires-Python: >=3.10
License-File: LICENSE
Requires-Dist: numpy >=1.26
Requires-Dist: pandas >=2.2
Requires-Dist: ase >=3.22
Requires-Dist: matplotlib >=3.6
Requires-Dist: tqdm >=4.64
Requires-Dist: scikit-learn >=1.1
Requires-Dist: requests >=2.26
Requires-Dist: bitarray >=2.4.1
